README.txt
setup.cfg
setup.py
docs/HISTORY.txt
docs/INSTALL.txt
docs/LICENSE.GPL
docs/LICENSE.txt
elektrika/__init__.py
elektrika.openx.egg-info/PKG-INFO
elektrika.openx.egg-info/SOURCES.txt
elektrika.openx.egg-info/dependency_links.txt
elektrika.openx.egg-info/entry_points.txt
elektrika.openx.egg-info/namespace_packages.txt
elektrika.openx.egg-info/not-zip-safe
elektrika.openx.egg-info/requires.txt
elektrika.openx.egg-info/top_level.txt
elektrika/openx/__init__.py
elektrika/openx/configure.zcml
elektrika/openx/interfaces.py
elektrika/openx/tests.py
elektrika/openx/utilities.py
elektrika/openx/browser/__init__.py
elektrika/openx/browser/banner.pt
elektrika/openx/browser/configure.zcml
elektrika/openx/browser/elektrika.openx.css
elektrika/openx/browser/openx.py
elektrika/openx/browser/viewlets.py
elektrika/openx/portlets/__init__.py
elektrika/openx/portlets/configure.zcml
elektrika/openx/portlets/openx_portlet.pt
elektrika/openx/portlets/openx_portlet.py
elektrika/openx/profiles/default/cssregistry.xml
elektrika/openx/profiles/default/metadata.xml
elektrika/openx/profiles/default/portlets.xml