Metadata-Version: 1.0
Name: elektrika.openx
Version: 1.3
Summary: OpenX invoication code, portlet, viewlets
Home-page: http://pypi.python.org/pypi/elektrika.openx
Author: Radim Novotny
Author-email: novotny.radim@gmail.com
License: GPL
Keywords: openx ad
Platform: UNKNOWN
Classifier: Framework :: Plone
Classifier: Programming Language :: Python
Classifier: Topic :: Software Development :: Libraries :: Python Modules
